[
  {
    "name": "com.getpcpanel.cpp.windows.SndCtrlWindows",
    "allDeclaredMethods": true,
    "allDeclaredConstructors": true,
    "allDeclaredFields": true
  },
  {
    "name": "com.getpcpanel.cpp.windows.WindowsAudioDevice",
    "allDeclaredMethods": true,
    "allDeclaredConstructors": true,
    "allDeclaredFields": true
  },
  {
    "name": "com.getpcpanel.cpp.AudioDevice",
    "allDeclaredMethods": true,
    "allDeclaredConstructors": true,
    "allDeclaredFields": true
  },
  {
    "name": "com.getpcpanel.cpp.AudioSession",
    "allDeclaredMethods": true,
    "allDeclaredConstructors": true,
    "allDeclaredFields": true
  },
  {
    "name": "java.lang.Object",
    "allDeclaredMethods": true,
    "allDeclaredConstructors": true,
    "allDeclaredFields": true
  },
  {
    "name": "java.lang.Class",
    "allDeclaredMethods": true,
    "allDeclaredConstructors": true,
    "allDeclaredFields": true
  },
  {
    "name": "java.lang.ClassLoader",
    "allDeclaredMethods": true,
    "allDeclaredConstructors": true,
    "allDeclaredFields": true
  },
  {
    "name": "java.lang.String",
    "allDeclaredMethods": true,
    "allDeclaredConstructors": true,
    "allDeclaredFields": true
  },
  {
    "name": "java.lang.Number",
    "allDeclaredMethods": true,
    "allDeclaredConstructors": true,
    "allDeclaredFields": true
  },
  {
    "name": "java.lang.Boolean",
    "allDeclaredMethods": true,
    "allDeclaredConstructors": true,
    "allDeclaredFields": true
  },
  {
    "name": "java.lang.Byte",
    "allDeclaredMethods": true,
    "allDeclaredConstructors": true,
    "allDeclaredFields": true
  },
  {
    "name": "java.lang.Character",
    "allDeclaredMethods": true,
    "allDeclaredConstructors": true,
    "allDeclaredFields": true
  },
  {
    "name": "java.lang.Short",
    "allDeclaredMethods": true,
    "allDeclaredConstructors": true,
    "allDeclaredFields": true
  },
  {
    "name": "java.lang.Integer",
    "allDeclaredMethods": true,
    "allDeclaredConstructors": true,
    "allDeclaredFields": true
  },
  {
    "name": "java.lang.Long",
    "allDeclaredMethods": true,
    "allDeclaredConstructors": true,
    "allDeclaredFields": true
  },
  {
    "name": "java.lang.Float",
    "allDeclaredMethods": true,
    "allDeclaredConstructors": true,
    "allDeclaredFields": true
  },
  {
    "name": "java.lang.Double",
    "allDeclaredMethods": true,
    "allDeclaredConstructors": true,
    "allDeclaredFields": true
  },
  {
    "name": "java.lang.Void",
    "allDeclaredMethods": true,
    "allDeclaredConstructors": true,
    "allDeclaredFields": true
  },
  {
    "name": "java.lang.reflect.Method",
    "allDeclaredMethods": true,
    "allDeclaredConstructors": true,
    "allDeclaredFields": true
  },
  {
    "name": "java.lang.reflect.Field",
    "allDeclaredMethods": true,
    "allDeclaredConstructors": true,
    "allDeclaredFields": true
  },
  {
    "name": "java.lang.reflect.Constructor",
    "allDeclaredMethods": true,
    "allDeclaredConstructors": true,
    "allDeclaredFields": true
  },
  {
    "name": "java.lang.reflect.AccessibleObject",
    "allDeclaredMethods": true,
    "allDeclaredConstructors": true,
    "allDeclaredFields": true
  },
  {
    "name": "java.lang.reflect.Proxy",
    "allDeclaredMethods": true,
    "allDeclaredConstructors": true,
    "allDeclaredFields": true
  },
  {
    "name": "java.lang.reflect.InvocationHandler",
    "allDeclaredMethods": true,
    "allDeclaredConstructors": true,
    "allDeclaredFields": true
  },
  {
    "name": "java.lang.ref.WeakReference",
    "allDeclaredMethods": true,
    "allDeclaredConstructors": true,
    "allDeclaredFields": true
  },
  {
    "name": "java.lang.ref.Reference",
    "allDeclaredMethods": true,
    "allDeclaredConstructors": true,
    "allDeclaredFields": true
  },
  {
    "name": "java.util.Collection",
    "allDeclaredMethods": true,
    "allDeclaredConstructors": true,
    "allDeclaredFields": true
  },
  {
    "name": "java.util.ArrayList",
    "allDeclaredMethods": true,
    "allDeclaredConstructors": true,
    "allDeclaredFields": true
  },
  {
    "name": "java.nio.Buffer",
    "allDeclaredMethods": true,
    "allDeclaredConstructors": true,
    "allDeclaredFields": true
  },
  {
    "name": "java.nio.ByteBuffer",
    "allDeclaredMethods": true,
    "allDeclaredConstructors": true,
    "allDeclaredFields": true
  },
  {
    "name": "java.nio.CharBuffer",
    "allDeclaredMethods": true,
    "allDeclaredConstructors": true,
    "allDeclaredFields": true
  },
  {
    "name": "java.nio.ShortBuffer",
    "allDeclaredMethods": true,
    "allDeclaredConstructors": true,
    "allDeclaredFields": true
  },
  {
    "name": "java.nio.IntBuffer",
    "allDeclaredMethods": true,
    "allDeclaredConstructors": true,
    "allDeclaredFields": true
  },
  {
    "name": "java.nio.LongBuffer",
    "allDeclaredMethods": true,
    "allDeclaredConstructors": true,
    "allDeclaredFields": true
  },
  {
    "name": "java.nio.FloatBuffer",
    "allDeclaredMethods": true,
    "allDeclaredConstructors": true,
    "allDeclaredFields": true
  },
  {
    "name": "java.nio.DoubleBuffer",
    "allDeclaredMethods": true,
    "allDeclaredConstructors": true,
    "allDeclaredFields": true
  },
  {
    "name": "com.sun.jna.AltCallingConvention",
    "allDeclaredMethods": true,
    "allDeclaredConstructors": true,
    "allDeclaredFields": true
  },
  {
    "name": "com.sun.jna.Callback",
    "allDeclaredMethods": true,
    "allDeclaredConstructors": true,
    "allDeclaredFields": true
  },
  {
    "name": "com.sun.jna.Callback$UncaughtExceptionHandler",
    "allDeclaredMethods": true,
    "allDeclaredConstructors": true,
    "allDeclaredFields": true
  },
  {
    "name": "com.sun.jna.CallbackParameterContext",
    "allDeclaredMethods": true,
    "allDeclaredConstructors": true,
    "allDeclaredFields": true
  },
  {
    "name": "com.sun.jna.CallbackProxy",
    "allDeclaredMethods": true,
    "allDeclaredConstructors": true,
    "allDeclaredFields": true
  },
  {
    "name": "com.sun.jna.CallbackReference",
    "allDeclaredMethods": true,
    "allDeclaredConstructors": true,
    "allDeclaredFields": true
  },
  {
    "name": "com.sun.jna.CallbackReference$AttachOptions",
    "allDeclaredMethods": true,
    "allDeclaredConstructors": true,
    "allDeclaredFields": true
  },
  {
    "name": "com.sun.jna.CallbackReference$CallbackReferenceDisposer",
    "allDeclaredMethods": true,
    "allDeclaredConstructors": true,
    "allDeclaredFields": true
  },
  {
    "name": "com.sun.jna.CallbackReference$DefaultCallbackProxy",
    "allDeclaredMethods": true,
    "allDeclaredConstructors": true,
    "allDeclaredFields": true
  },
  {
    "name": "com.sun.jna.CallbackReference$NativeFunctionHandler",
    "allDeclaredMethods": true,
    "allDeclaredConstructors": true,
    "allDeclaredFields": true
  },
  {
    "name": "com.sun.jna.CallbackResultContext",
    "allDeclaredMethods": true,
    "allDeclaredConstructors": true,
    "allDeclaredFields": true
  },
  {
    "name": "com.sun.jna.CallbackThreadInitializer",
    "allDeclaredMethods": true,
    "allDeclaredConstructors": true,
    "allDeclaredFields": true
  },
  {
    "name": "com.sun.jna.DefaultTypeMapper",
    "allDeclaredMethods": true,
    "allDeclaredConstructors": true,
    "allDeclaredFields": true
  },
  {
    "name": "com.sun.jna.DefaultTypeMapper$Entry",
    "allDeclaredMethods": true,
    "allDeclaredConstructors": true,
    "allDeclaredFields": true
  },
  {
    "name": "com.sun.jna.FromNativeContext",
    "allDeclaredMethods": true,
    "allDeclaredConstructors": true,
    "allDeclaredFields": true
  },
  {
    "name": "com.sun.jna.FromNativeConverter",
    "allDeclaredMethods": true,
    "allDeclaredConstructors": true,
    "allDeclaredFields": true
  },
  {
    "name": "com.sun.jna.Function",
    "allDeclaredMethods": true,
    "allDeclaredConstructors": true,
    "allDeclaredFields": true
  },
  {
    "name": "com.sun.jna.Function$NativeMappedArray",
    "allDeclaredMethods": true,
    "allDeclaredConstructors": true,
    "allDeclaredFields": true
  },
  {
    "name": "com.sun.jna.Function$PointerArray",
    "allDeclaredMethods": true,
    "allDeclaredConstructors": true,
    "allDeclaredFields": true
  },
  {
    "name": "com.sun.jna.Function$PostCallRead",
    "allDeclaredMethods": true,
    "allDeclaredConstructors": true,
    "allDeclaredFields": true
  },
  {
    "name": "com.sun.jna.FunctionMapper",
    "allDeclaredMethods": true,
    "allDeclaredConstructors": true,
    "allDeclaredFields": true
  },
  {
    "name": "com.sun.jna.FunctionParameterContext",
    "allDeclaredMethods": true,
    "allDeclaredConstructors": true,
    "allDeclaredFields": true
  },
  {
    "name": "com.sun.jna.FunctionResultContext",
    "allDeclaredMethods": true,
    "allDeclaredConstructors": true,
    "allDeclaredFields": true
  },
  {
    "name": "com.sun.jna.IntegerType",
    "allDeclaredMethods": true,
    "allDeclaredConstructors": true,
    "allDeclaredFields": true
  },
  {
    "name": "com.sun.jna.internal.Cleaner",
    "allDeclaredMethods": true,
    "allDeclaredConstructors": true,
    "allDeclaredFields": true
  },
  {
    "name": "com.sun.jna.internal.Cleaner$Cleanable",
    "allDeclaredMethods": true,
    "allDeclaredConstructors": true,
    "allDeclaredFields": true
  },
  {
    "name": "com.sun.jna.internal.Cleaner$CleanerRef",
    "allDeclaredMethods": true,
    "allDeclaredConstructors": true,
    "allDeclaredFields": true
  },
  {
    "name": "com.sun.jna.internal.ReflectionUtils",
    "allDeclaredMethods": true,
    "allDeclaredConstructors": true,
    "allDeclaredFields": true
  },
  {
    "name": "com.sun.jna.InvocationMapper",
    "allDeclaredMethods": true,
    "allDeclaredConstructors": true,
    "allDeclaredFields": true
  },
  {
    "name": "com.sun.jna.JNIEnv",
    "allDeclaredMethods": true,
    "allDeclaredConstructors": true,
    "allDeclaredFields": true
  },
  {
    "name": "com.sun.jna.Klass",
    "allDeclaredMethods": true,
    "allDeclaredConstructors": true,
    "allDeclaredFields": true
  },
  {
    "name": "com.sun.jna.LastErrorException",
    "allDeclaredMethods": true,
    "allDeclaredConstructors": true,
    "allDeclaredFields": true
  },
  {
    "name": "com.sun.jna.Library",
    "allDeclaredMethods": true,
    "allDeclaredConstructors": true,
    "allDeclaredFields": true
  },
  {
    "name": "com.sun.jna.Library$Handler",
    "allDeclaredMethods": true,
    "allDeclaredConstructors": true,
    "allDeclaredFields": true
  },
  {
    "name": "com.sun.jna.Library$Handler$FunctionInfo",
    "allDeclaredMethods": true,
    "allDeclaredConstructors": true,
    "allDeclaredFields": true
  },
  {
    "name": "com.sun.jna.Memory",
    "allDeclaredMethods": true,
    "allDeclaredConstructors": true,
    "allDeclaredFields": true
  },
  {
    "name": "com.sun.jna.Memory$MemoryDisposer",
    "allDeclaredMethods": true,
    "allDeclaredConstructors": true,
    "allDeclaredFields": true
  },
  {
    "name": "com.sun.jna.Memory$SharedMemory",
    "allDeclaredMethods": true,
    "allDeclaredConstructors": true,
    "allDeclaredFields": true
  },
  {
    "name": "com.sun.jna.MethodParameterContext",
    "allDeclaredMethods": true,
    "allDeclaredConstructors": true,
    "allDeclaredFields": true
  },
  {
    "name": "com.sun.jna.MethodResultContext",
    "allDeclaredMethods": true,
    "allDeclaredConstructors": true,
    "allDeclaredFields": true
  },
  {
    "name": "com.sun.jna.Native",
    "allDeclaredMethods": true,
    "allDeclaredConstructors": true,
    "allDeclaredFields": true
  },
  {
    "name": "com.sun.jna.Native$AWT",
    "allDeclaredMethods": true,
    "allDeclaredConstructors": true,
    "allDeclaredFields": true
  },
  {
    "name": "com.sun.jna.Native$Buffers",
    "allDeclaredMethods": true,
    "allDeclaredConstructors": true,
    "allDeclaredFields": true
  },
  {
    "name": "com.sun.jna.Native$ffi_callback",
    "allDeclaredMethods": true,
    "allDeclaredConstructors": true,
    "allDeclaredFields": true
  },
  {
    "name": "com.sun.jna.NativeLibrary",
    "allDeclaredMethods": true,
    "allDeclaredConstructors": true,
    "allDeclaredFields": true
  },
  {
    "name": "com.sun.jna.NativeLibrary$NativeLibraryDisposer",
    "allDeclaredMethods": true,
    "allDeclaredConstructors": true,
    "allDeclaredFields": true
  },
  {
    "name": "com.sun.jna.NativeLong",
    "allDeclaredMethods": true,
    "allDeclaredConstructors": true,
    "allDeclaredFields": true
  },
  {
    "name": "com.sun.jna.NativeMapped",
    "allDeclaredMethods": true,
    "allDeclaredConstructors": true,
    "allDeclaredFields": true
  },
  {
    "name": "com.sun.jna.NativeMappedConverter",
    "allDeclaredMethods": true,
    "allDeclaredConstructors": true,
    "allDeclaredFields": true
  },
  {
    "name": "com.sun.jna.NativeString",
    "allDeclaredMethods": true,
    "allDeclaredConstructors": true,
    "allDeclaredFields": true
  },
  {
    "name": "com.sun.jna.NativeString$StringMemory",
    "allDeclaredMethods": true,
    "allDeclaredConstructors": true,
    "allDeclaredFields": true
  },
  {
    "name": "com.sun.jna.Platform",
    "allDeclaredMethods": true,
    "allDeclaredConstructors": true,
    "allDeclaredFields": true
  },
  {
    "name": "com.sun.jna.Pointer",
    "allDeclaredMethods": true,
    "allDeclaredConstructors": true,
    "allDeclaredFields": true
  },
  {
    "name": "com.sun.jna.Pointer$Opaque",
    "allDeclaredMethods": true,
    "allDeclaredConstructors": true,
    "allDeclaredFields": true
  },
  {
    "name": "com.sun.jna.PointerType",
    "allDeclaredMethods": true,
    "allDeclaredConstructors": true,
    "allDeclaredFields": true
  },
  {
    "name": "com.sun.jna.StringArray",
    "allDeclaredMethods": true,
    "allDeclaredConstructors": true,
    "allDeclaredFields": true
  },
  {
    "name": "com.sun.jna.Structure",
    "allDeclaredMethods": true,
    "allDeclaredConstructors": true,
    "allDeclaredFields": true
  },
  {
    "name": "com.sun.jna.Structure$AutoAllocated",
    "allDeclaredMethods": true,
    "allDeclaredConstructors": true,
    "allDeclaredFields": true
  },
  {
    "name": "com.sun.jna.Structure$ByReference",
    "allDeclaredMethods": true,
    "allDeclaredConstructors": true,
    "allDeclaredFields": true
  },
  {
    "name": "com.sun.jna.Structure$ByValue",
    "allDeclaredMethods": true,
    "allDeclaredConstructors": true,
    "allDeclaredFields": true
  },
  {
    "name": "com.sun.jna.Structure$FFIType",
    "allDeclaredMethods": true,
    "allDeclaredConstructors": true,
    "allDeclaredFields": true
  },
  {
    "name": "com.sun.jna.Structure$FFIType$FFITypes",
    "allDeclaredMethods": true,
    "allDeclaredConstructors": true,
    "allDeclaredFields": true
  },
  {
    "name": "com.sun.jna.Structure$FFIType$size_t",
    "allDeclaredMethods": true,
    "allDeclaredConstructors": true,
    "allDeclaredFields": true
  },
  {
    "name": "com.sun.jna.Structure$FieldOrder",
    "allDeclaredMethods": true,
    "allDeclaredConstructors": true,
    "allDeclaredFields": true
  },
  {
    "name": "com.sun.jna.Structure$LayoutInfo",
    "allDeclaredMethods": true,
    "allDeclaredConstructors": true,
    "allDeclaredFields": true
  },
  {
    "name": "com.sun.jna.Structure$NativeStringTracking",
    "allDeclaredMethods": true,
    "allDeclaredConstructors": true,
    "allDeclaredFields": true
  },
  {
    "name": "com.sun.jna.Structure$StructField",
    "allDeclaredMethods": true,
    "allDeclaredConstructors": true,
    "allDeclaredFields": true
  },
  {
    "name": "com.sun.jna.Structure$StructureSet",
    "allDeclaredMethods": true,
    "allDeclaredConstructors": true,
    "allDeclaredFields": true
  },
  {
    "name": "com.sun.jna.StructureReadContext",
    "allDeclaredMethods": true,
    "allDeclaredConstructors": true,
    "allDeclaredFields": true
  },
  {
    "name": "com.sun.jna.StructureWriteContext",
    "allDeclaredMethods": true,
    "allDeclaredConstructors": true,
    "allDeclaredFields": true
  },
  {
    "name": "com.sun.jna.ToNativeContext",
    "allDeclaredMethods": true,
    "allDeclaredConstructors": true,
    "allDeclaredFields": true
  },
  {
    "name": "com.sun.jna.ToNativeConverter",
    "allDeclaredMethods": true,
    "allDeclaredConstructors": true,
    "allDeclaredFields": true
  },
  {
    "name": "com.sun.jna.TypeConverter",
    "allDeclaredMethods": true,
    "allDeclaredConstructors": true,
    "allDeclaredFields": true
  },
  {
    "name": "com.sun.jna.TypeMapper",
    "allDeclaredMethods": true,
    "allDeclaredConstructors": true,
    "allDeclaredFields": true
  },
  {
    "name": "com.sun.jna.Union",
    "allDeclaredMethods": true,
    "allDeclaredConstructors": true,
    "allDeclaredFields": true
  },
  {
    "name": "com.sun.jna.VarArgsChecker",
    "allDeclaredMethods": true,
    "allDeclaredConstructors": true,
    "allDeclaredFields": true
  },
  {
    "name": "com.sun.jna.Version",
    "allDeclaredMethods": true,
    "allDeclaredConstructors": true,
    "allDeclaredFields": true
  },
  {
    "name": "com.sun.jna.WeakMemoryHolder",
    "allDeclaredMethods": true,
    "allDeclaredConstructors": true,
    "allDeclaredFields": true
  },
  {
    "name": "com.sun.jna.WString",
    "allDeclaredMethods": true,
    "allDeclaredConstructors": true,
    "allDeclaredFields": true
  },
  {
    "name": "com.sun.jna.ptr.ByReference",
    "allDeclaredMethods": true,
    "allDeclaredConstructors": true,
    "allDeclaredFields": true
  },
  {
    "name": "com.sun.jna.ptr.ByteByReference",
    "allDeclaredMethods": true,
    "allDeclaredConstructors": true,
    "allDeclaredFields": true
  },
  {
    "name": "com.sun.jna.ptr.DoubleByReference",
    "allDeclaredMethods": true,
    "allDeclaredConstructors": true,
    "allDeclaredFields": true
  },
  {
    "name": "com.sun.jna.ptr.FloatByReference",
    "allDeclaredMethods": true,
    "allDeclaredConstructors": true,
    "allDeclaredFields": true
  },
  {
    "name": "com.sun.jna.ptr.IntByReference",
    "allDeclaredMethods": true,
    "allDeclaredConstructors": true,
    "allDeclaredFields": true
  },
  {
    "name": "com.sun.jna.ptr.LongByReference",
    "allDeclaredMethods": true,
    "allDeclaredConstructors": true,
    "allDeclaredFields": true
  },
  {
    "name": "com.sun.jna.ptr.NativeLongByReference",
    "allDeclaredMethods": true,
    "allDeclaredConstructors": true,
    "allDeclaredFields": true
  },
  {
    "name": "com.sun.jna.ptr.PointerByReference",
    "allDeclaredMethods": true,
    "allDeclaredConstructors": true,
    "allDeclaredFields": true
  },
  {
    "name": "com.sun.jna.ptr.ShortByReference",
    "allDeclaredMethods": true,
    "allDeclaredConstructors": true,
    "allDeclaredFields": true
  },
  {
    "name": "com.sun.jna.win32.DLLCallback",
    "allDeclaredMethods": true,
    "allDeclaredConstructors": true,
    "allDeclaredFields": true
  },
  {
    "name": "com.sun.jna.win32.StdCall",
    "allDeclaredMethods": true,
    "allDeclaredConstructors": true,
    "allDeclaredFields": true
  },
  {
    "name": "com.sun.jna.win32.StdCallFunctionMapper",
    "allDeclaredMethods": true,
    "allDeclaredConstructors": true,
    "allDeclaredFields": true
  },
  {
    "name": "com.sun.jna.win32.StdCallLibrary",
    "allDeclaredMethods": true,
    "allDeclaredConstructors": true,
    "allDeclaredFields": true
  },
  {
    "name": "com.sun.jna.win32.StdCallLibrary$StdCallCallback",
    "allDeclaredMethods": true,
    "allDeclaredConstructors": true,
    "allDeclaredFields": true
  },
  {
    "name": "com.sun.jna.win32.W32APIFunctionMapper",
    "allDeclaredMethods": true,
    "allDeclaredConstructors": true,
    "allDeclaredFields": true
  },
  {
    "name": "com.sun.jna.win32.W32APIOptions",
    "allDeclaredMethods": true,
    "allDeclaredConstructors": true,
    "allDeclaredFields": true
  },
  {
    "name": "com.sun.jna.win32.W32APITypeMapper",
    "allDeclaredMethods": true,
    "allDeclaredConstructors": true,
    "allDeclaredFields": true
  }
]